qPython3-1.0.1.dist-info/LICENSE
qPython3-1.0.1.dist-info/METADATA
qPython3-1.0.1.dist-info/top_level.txt
qPython3-1.0.1.dist-info/RECORD
qPython3-1.0.1.dist-info/WHEEL
qPython3-1.0.1.data/data/CHANGELOG.txt
qPython3-1.0.1.data/data/LICENSE
qPython3-1.0.1.data/data/requirements.txt
qPython3-1.0.1.data/data/README.rst
qpython/qwriter.py
qpython/qtemporal.py
qpython/_pandas.py
qpython/fastutils.cpython-37m-x86_64-linux-gnu.so
qpython/utils.py
qpython/qtype.py
qpython/qreader.py
qpython/fastutils.pyx
qpython/qconnection.py
qpython/__init__.py
qpython/qcollection.py
